loglizer/__init__.py
loglizer/dataloader.py
loglizer/preprocessing.py
loglizer/utils.py
loglizer/models/DecisionTree.py
loglizer/models/DeepLog.py
loglizer/models/InvariantsMiner.py
loglizer/models/IsolationForest.py
loglizer/models/LR.py
loglizer/models/LogClustering.py
loglizer/models/PCA.py
loglizer/models/SVM.py
loglizer/models/__init__.py
loglizer-1.0.dist-info/LICENSE
loglizer-1.0.dist-info/METADATA
loglizer-1.0.dist-info/WHEEL
loglizer-1.0.dist-info/top_level.txt
loglizer-1.0.dist-info/RECORD
